termy/__init__.py
termy/__main__.py
termy/constants.py
termy/controller/__init__.py
termy/controller/controller.py
termy/exception/__init__.py
termy/exception/custom_exceptions.py
termy/resources/__init__.py
termy/service/__init__.py
termy/service/aunthenticator/__init__.py
termy/service/aunthenticator/authenticate.py
termy/service/content_extractor/__init__.py
termy/service/content_extractor/get_sheet_content.py
termy/service/flow_handler/__init__.py
termy/service/flow_handler/handle_flows.py
termy/service/gpt_client/__init__.py
termy/service/gpt_client/gpt3_terminal_client.py
termy/utils/__init__.py
termy/utils/utils.py
termy-0.0.17.dist-info/LICENSE
termy-0.0.17.dist-info/METADATA
termy-0.0.17.dist-info/WHEEL
termy-0.0.17.dist-info/entry_points.txt
termy-0.0.17.dist-info/top_level.txt
termy-0.0.17.dist-info/RECORD
