Metadata-Version: 2.1
Name: termy
Version: 0.0.17
Summary: A lightweight terminal assistant to give a natural language interface to your terminal commands
Home-page: UNKNOWN
Author: Dingu Sagar, Bhanu Rekha, Divya Priya
Author-email: <termydbd@gmail.com>
License: UNKNOWN
Project-URL: Github, https://github.com/dingusagar/termy
Keywords: python,termy,terminal assistant,terminast,terminal alias,command automation
Platform: UNKNOWN
Classifier: Development Status :: 5 - Production/Stable
Classifier: Intended Audience :: Developers
Classifier: Programming Language :: Python :: 3
Classifier: Operating System :: Unix
Classifier: Operating System :: MacOS :: MacOS X
Classifier: Operating System :: Microsoft :: Windows
License-File: LICENSE
Requires-Dist: pandas
Requires-Dist: rapidfuzz
Requires-Dist: google-api-python-client
Requires-Dist: google-auth-httplib2
Requires-Dist: google-auth-oauthlib
Requires-Dist: colorama
Requires-Dist: tqdm
Requires-Dist: cryptography
Requires-Dist: art
Requires-Dist: openai
